rtl/data_memory.sv
module data_memory(

    input logic clk,
    input logic write_en,
    input logic [31:0] addr,
    input logic [31:0] write_data,
    output logic [31:0] read_data
);

logic [7:0] addr_index;
logic [31:0] memory [255:0];

initial begin
    $readmemh("C:/Users/User/Desktop/project risk v/sim/data.hex",memory);
end

always_ff@(posedge clk) begin
    if(write_en) begin
        memory[addr_index] <= write_data;
    end
end


assign addr_index = addr[9:2];
assign read_data = memory[addr_index];

endmodule

rtl/alu.sv
module alu(
    input [31:0] a,b,
    input [3:0] alu_op,
    output logic [31:0] result,
    output logic zero
);

logic [4:0] shft_amt;

localparam
    ADD = 4'b0000,
    SUB = 4'b0001,
    AND = 4'b0010,
    OR  = 4'b0011,
    XOR = 4'b0100,
    SHL = 4'b0101,
    SHR = 4'b0110,
    SHRA = 4'b0111,
    SLT = 4'b1000,
    SLTU= 4'b1001;

always_comb begin
    
    case(alu_op) 
        
        ADD : result = a + b;

        SUB : result = a - b;
        
        AND : result = a & b;

        OR : result = a | b;

        XOR : result = a ^ b;

        SHL : result = a << shft_amt;

        SHR : result = a >> shft_amt;

        SHRA: result = $signed(a) >>> shft_amt;

        SLT : result = ($signed(a) < $signed(b)) ? 32'b1 : 32'b0;

        SLTU: result = (a < b) ? 32'b1 : 32'b0;

        default: result = 32'b0;

        endcase

        
    end
    

assign zero = (result == 32'b0) ? 1'b1 : 1'b0;
assign shft_amt = b[4:0];


    
endmodule

rtl/sign_extender.sv
module sign_extender(

    input logic [2:0] imm_src,
    input logic [31:0] instruction,
    output logic [31:0] extended
);

localparam i_type = 3'b000;
localparam s_type = 3'b001;
localparam b_type = 3'b010;
localparam u_type = 3'b011;
localparam j_type = 3'b100;

always@(*) begin
    case(imm_src)

    i_type: extended = {{20{instruction[31]}}, instruction[31:20]};

    s_type: extended = {{20{instruction[31]}}, instruction[31:25], instruction[11:7]};

    b_type: extended = {{20{instruction[31]}}, instruction[7], instruction[30:25], instruction[11:8], 1'b0};

    u_type: extended = {{instruction[31:12]}, 12'b0};

    j_type: extended = {{12{instruction[31]}}, instruction[31], instruction[19:12], instruction[20], instruction[30:21], 1'b0};

    default: extended = 32'b0;

    endcase

    end

endmodule

rtl/rtl/register_file.sv
module regfile(
    input logic clk,rst,write_en,
    input logic [4:0] read_addr1, read_addr2, write_addr,
    input logic [31:0] write_data,
    output logic [31:0] read_data1, read_data2
);

logic [31:0] registers [31:0];

always_ff@(posedge clk or posedge rst) begin
    if(rst) begin
        for(int i=0;i<32;i++) begin
            registers[i]<= 32'b0;
        end
    end else if(write_en & (write_addr != 5'b0)) 
        registers[write_addr] <= write_data;
    
    end

assign read_data1 = (read_addr1 == 5'b0) ? 32'b0 : registers[read_addr1];
assign read_data2 = (read_addr2 == 5'b0) ? 32'b0 : registers[read_addr2];

endmodule

rtl/instruction_memory.sv
module instruction_memory(

    input logic [31:0] addr,
    output logic [31:0] instruction
);

logic [31:0] instruction_mem [0:255];

initial begin
    $readmemh("instruction_data_sum_arr.hex", instruction_mem);
end

assign instruction = instruction_mem[addr[9:2]]; // word aligned address + reduced to 8 bits for 256 instructions

endmodule

rtl/rtl/pc.sv
module pc(
    input logic clk,
    input logic rst,
    input logic pc_en,
    input logic [31:0] pc_in,
    output logic [31:0] pc_out
);

always_ff@(posedge clk or posedge rst) begin
    if(rst) begin
        pc_out <= 32'b0;
    end else if(pc_en) begin
        pc_out <= pc_in;
    end

end

endmodule

rtl/rtl/datapath.sv
module datapath(

    input logic clk,
    input logic rst,
    input logic alu_src,
    input logic [1:0] pc_src,
    input logic reg_write,
    input logic [3:0] alu_ctrl,
    input logic [2:0] imm_src,
    input logic mem_write,
    input logic [2:0] result_src,
    output logic [6:0] op_code,
    output logic bit30func7,
    output logic [2:0] func3,
    output logic zero_flag
);

logic [31:0] pc_current;
logic [31:0] pc_next;
logic [31:0] instruction;
logic [31:0] read_data1;
logic [31:0] read_data2;
logic [31:0] extended;
logic [31:0] b;
logic [31:0] alu_result;
logic zero;
logic [31:0] mem_read_data;
logic [31:0] write_back_data;
logic [31:0] pc_target;
logic [31:0] pc_inc;


//temp control wires
/////////

pc pc_instance(
    .clk(clk),
    .rst(rst),
    .pc_en(1'b1), //temp
    .pc_in(pc_next),
    .pc_out(pc_current)
);

instruction_memory instruction_memory_instance(
    .addr(pc_current),
    .instruction(instruction)
);

regfile regfile_instance(
    .clk(clk),
    .rst(rst),
    .write_en(reg_write),
    .read_addr1(instruction[19:15]),
    .read_addr2(instruction[24:20]),
    .write_addr(instruction[11:7]),
    .write_data(write_back_data), 
    .read_data1(read_data1),
    .read_data2(read_data2)
);

sign_extender sign_extender_instance(
    .imm_src(imm_src), // 
    .instruction(instruction),
    .extended(extended)
);

alu alu_instance(
    .a(read_data1),
    .b(b),
    .alu_op(alu_ctrl),
    .zero(zero),
    .result(alu_result)
);

data_memory data_memory_instance(
    .clk(clk),
    .write_en(mem_write),//
    .addr(alu_result),
    .write_data(read_data2),
    .read_data(mem_read_data)
);







always_comb begin
    case(result_src)
        3'b000: write_back_data = alu_result;
        3'b001: write_back_data = mem_read_data;
        3'b010: write_back_data = pc_inc;
        3'b011: write_back_data = extended;
        3'b100: write_back_data = pc_target;
        default: write_back_data = 32'b0;
    endcase
end

always_comb begin
    case(pc_src)
    2'b00: pc_next = pc_inc;
    2'b01: pc_next = pc_target;
    2'b10: pc_next = alu_result;
    default: pc_next = pc_inc;
    endcase
end

assign pc_inc = pc_current + 32'd4;
assign pc_target = pc_current + extended;
assign b = (alu_src)? extended:read_data2;
assign op_code = instruction[6:0];
assign func3 = instruction[14:12];
assign bit30func7 = instruction[30];
assign zero_flag = zero;


endmodule

rtl/control_unit_alu_decoder.sv
module control_unit_alu_decoder(
    input logic [1:0] alu_op,
    input logic [2:0] func3,
    input logic bit30func7,
    input logic op5,
    output logic [3:0] alu_ctrl
);

localparam add = 2'b00;
localparam sub = 2'b01;
localparam other = 2'b10;

always_comb begin 
    case(alu_op)
        add: alu_ctrl = 4'b0000;
        sub: alu_ctrl = 4'b0001;
        other: begin
            case(func3)
                3'b000: begin
                    if(op5 & bit30func7)
                        alu_ctrl = 4'b0001;
                    else
                        alu_ctrl = 4'b0000;
                end
                3'b010: alu_ctrl = 4'b1000;
               
                3'b110: alu_ctrl = 4'b0011;

                3'b111: alu_ctrl = 4'b0010;  

                default: alu_ctrl = 4'b0000;
            endcase
        end
        default: alu_ctrl = 4'b0000;

    endcase
    
end


endmodule

rtl/control_unit_main_decoder.sv
module control_unit_main_decoder(
input logic [6:0] op_code,
output logic branch,
output logic jump,
output logic jalr,
output logic [2:0] result_src,
output logic mem_write,
output logic [1:0] alu_op, //00 add 01 sub 10 let func3and7 decide
output logic alu_src,
output logic [2:0] imm_ctrl,
output logic reg_write
);


localparam  lw = 7'b0000011;
localparam  sw = 7'b0100011;
localparam r_type = 7'b0110011;
localparam i_type = 7'b0010011;
localparam beq = 7'b1100011;
localparam jal = 7'b1101111;
localparam jalr_op = 7'b1100111;
localparam lui = 7'b0110111;
localparam auipc = 7'b0010111;
localparam nop = 13'b0000000000000;


always_comb begin
    case(op_code)

        lw:      {jalr, jump, branch, result_src, mem_write, alu_op, alu_src, imm_ctrl, reg_write} = 14'b0_0_0_001_0_00_1_000_1;
        sw:      {jalr, jump, branch, result_src, mem_write, alu_op, alu_src, imm_ctrl, reg_write} = 14'b0_0_0_000_1_00_1_001_0;
        r_type:  {jalr, jump, branch, result_src, mem_write, alu_op, alu_src, imm_ctrl, reg_write} = 14'b0_0_0_000_0_10_0_000_1;
        i_type:  {jalr, jump, branch, result_src, mem_write, alu_op, alu_src, imm_ctrl, reg_write} = 14'b0_0_0_000_0_10_1_000_1;
        beq:     {jalr, jump, branch, result_src, mem_write, alu_op, alu_src, imm_ctrl, reg_write} = 14'b0_0_1_000_0_01_0_010_0;
        jal:     {jalr, jump, branch, result_src, mem_write, alu_op, alu_src, imm_ctrl, reg_write} = 14'b0_1_0_010_0_00_0_100_1;
        jalr_op: {jalr, jump, branch, result_src, mem_write, alu_op, alu_src, imm_ctrl, reg_write} = 14'b1_0_0_010_0_00_1_000_1;
        lui:     {jalr, jump, branch, result_src, mem_write, alu_op, alu_src, imm_ctrl, reg_write} = 14'b0_0_0_011_0_00_1_011_1; 
        auipc:   {jalr, jump, branch, result_src, mem_write, alu_op, alu_src, imm_ctrl, reg_write} = 14'b0_0_0_100_0_00_1_011_1; 
        default: {jalr, jump, branch, result_src, mem_write, alu_op, alu_src, imm_ctrl, reg_write} = nop;
    endcase
end


endmodule

rtl/control_unit.sv
module control_unit(

    input logic [6:0] op_code,
    input logic [2:0] func3,
    input logic bit30func7,
    input logic zero,
    output logic [1:0] pc_src,
    output logic [2:0] result_src,
    output logic mem_write,
    output logic [3:0] alu_ctrl,
    output logic alu_src,
    output logic [2:0] imm_ctrl,
    output logic reg_write
);

logic [1:0] alu_op;
logic branch;
logic jump;
logic jalr;

control_unit_main_decoder control_unit_main_decoder_instance(
    .op_code(op_code),
    .jump(jump),
    .jalr(jalr),
    .branch(branch),
    .result_src(result_src),
    .mem_write(mem_write),
    .alu_op(alu_op),
    .alu_src(alu_src),
    .imm_ctrl(imm_ctrl),
    .reg_write(reg_write)
);

control_unit_alu_decoder control_unit_alu_decoder_instance(
    .alu_op(alu_op),
    .func3(func3),
    .bit30func7(bit30func7),
    .op5(op_code[5]),
    .alu_ctrl(alu_ctrl)
);

assign pc_src = jalr ? 2'b10 : (jump | (branch & zero)) ? 2'b01 : 2'b00;

endmodule

rtl/rtl/risc_v_top.sv
module risc_v_top(
    input logic clk,
    input logic rst
);

logic alu_src;
logic [1:0] pc_src;
logic reg_write;
logic [3:0] alu_ctrl;
logic [2:0] imm_src;
logic mem_write;
logic [2:0] result_src;
logic [6:0] op_code;
logic bit30func7;
logic [2:0] func3;
logic zero_flag;

control_unit control_unit_instance(
    .op_code(op_code),
    .func3(func3),
    .bit30func7(bit30func7),
    .zero(zero_flag),
    .pc_src(pc_src),
    .result_src(result_src),
    .mem_write(mem_write),
    .alu_ctrl(alu_ctrl),
    .alu_src(alu_src),
    .imm_ctrl(imm_src),
    .reg_write(reg_write)
);

datapath datapath_instance(
    .clk(clk),
    .rst(rst),
    .alu_src(alu_src),
    .pc_src(pc_src),
    .reg_write(reg_write),
    .alu_ctrl(alu_ctrl),
    .imm_src(imm_src),
    .mem_write(mem_write),
    .result_src(result_src),
    .op_code(op_code),
    .bit30func7(bit30func7),
    .func3(func3),
    .zero_flag(zero_flag)
);

endmodule

tb/risc_v_top_tb.sv
module risc_v_top_tb;

    logic clk;
    logic rst;

    int clk_cycles = 0; //clock cycle counter

    risc_v_top dut(
        .clk(clk),
        .rst(rst)
    );

    always #5 clk = ~clk; //generate clock
    always_ff@(posedge clk) begin
        clk_cycles <= clk_cycles + 1;
    end

    initial begin
        $dumpfile("sim/dump.vcd"); //create a dump file
        $dumpvars(0, risc_v_top_tb);

        clk = 1'b0; //initialize system
        rst = 1'b1;
        #15

        rst = 1'b0;// let the system run
        #350

        if(dut.datapath_instance.data_memory_instance.memory[0] == 32'd15) 
            $display("success: 15 value is written to memory[0], clock cycles:%d", clk_cycles);
        else    
            $display("failed: failed to write 15 value to mem[0], clock cycles:%d", clk_cycles);

        if(dut.datapath_instance.regfile_instance.registers[2] == 32'd15 && dut.datapath_instance.regfile_instance.registers[1] == 32'd0) 
                 $display("success: 15 value is written to reg[2] and reg[1], clock cycles:%d", clk_cycles);
        else 
            $display("failed: failed to write 15 value to reg[2] and reg[1], clock cycles:%d", clk_cycles);
        $finish;
    end

endmodule

dump.vcd
$date
	Tue Sep 22 17:01:23 2026
$end
$version
	Icarus Verilog
$end
$timescale
	1s
$end
$scope module risc_v_top_tb $end
$var reg 1 ! clk $end
$var reg 1 " rst $end
$var integer 32 # clk_cycles [31:0] $end
$scope module dut $end
$var wire 1 ! clk $end
$var wire 1 " rst $end
$var wire 1 $ zero_flag $end
$var wire 3 % result_src [2:0] $end
$var wire 1 & reg_write $end
$var wire 2 ' pc_src [1:0] $end
$var wire 7 ( op_code [6:0] $end
$var wire 1 ) mem_write $end
$var wire 3 * imm_src [2:0] $end
$var wire 3 + func3 [2:0] $end
$var wire 1 , bit30func7 $end
$var wire 1 - alu_src $end
$var wire 4 . alu_ctrl [3:0] $end
$scope module control_unit_instance $end
$var wire 1 $ zero $end
$var wire 3 / result_src [2:0] $end
$var wire 1 & reg_write $end
$var wire 2 0 pc_src [1:0] $end
$var wire 7 1 op_code [6:0] $end
$var wire 1 ) mem_write $end
$var wire 1 2 jump $end
$var wire 1 3 jalr $end
$var wire 3 4 imm_ctrl [2:0] $end
$var wire 3 5 func3 [2:0] $end
$var wire 1 6 branch $end
$var wire 1 , bit30func7 $end
$var wire 1 - alu_src $end
$var wire 2 7 alu_op [1:0] $end
$var wire 4 8 alu_ctrl [3:0] $end
$scope module control_unit_alu_decoder_instance $end
$var wire 1 9 op5 $end
$var wire 3 : func3 [2:0] $end
$var wire 1 , bit30func7 $end
$var wire 2 ; alu_op [1:0] $end
$var reg 4 < alu_ctrl [3:0] $end
$upscope $end
$scope module control_unit_main_decoder_instance $end
$var wire 7 = op_code [6:0] $end
$var reg 2 > alu_op [1:0] $end
$var reg 1 - alu_src $end
$var reg 1 6 branch $end
$var reg 3 ? imm_ctrl [2:0] $end
$var reg 1 3 jalr $end
$var reg 1 2 jump $end
$var reg 1 ) mem_write $end
$var reg 1 & reg_write $end
$var reg 3 @ result_src [2:0] $end
$upscope $end
$upscope $end
$scope module datapath_instance $end
$var wire 4 A alu_ctrl [3:0] $end
$var wire 1 - alu_src $end
$var wire 1 ! clk $end
$var wire 3 B imm_src [2:0] $end
$var wire 1 ) mem_write $end
$var wire 2 C pc_src [1:0] $end
$var wire 1 & reg_write $end
$var wire 3 D result_src [2:0] $end
$var wire 1 " rst $end
$var wire 1 $ zero_flag $end
$var wire 1 E zero $end
$var wire 32 F read_data2 [31:0] $end
$var wire 32 G read_data1 [31:0] $end
$var wire 32 H pc_target [31:0] $end
$var wire 32 I pc_inc [31:0] $end
$var wire 32 J pc_current [31:0] $end
$var wire 7 K op_code [6:0] $end
$var wire 32 L mem_read_data [31:0] $end
$var wire 32 M instruction [31:0] $end
$var wire 3 N func3 [2:0] $end
$var wire 32 O extended [31:0] $end
$var wire 1 , bit30func7 $end
$var wire 32 P b [31:0] $end
$var wire 32 Q alu_result [31:0] $end
$var reg 32 R pc_next [31:0] $end
$var reg 32 S write_back_data [31:0] $end
$scope module alu_instance $end
$var wire 4 T alu_op [3:0] $end
$var wire 32 U b [31:0] $end
$var wire 1 E zero $end
$var wire 5 V shft_amt [4:0] $end
$var wire 32 W a [31:0] $end
$var reg 32 X result [31:0] $end
$upscope $end
$scope module data_memory_instance $end
$var wire 32 Y addr [31:0] $end
$var wire 1 ! clk $end
$var wire 32 Z read_data [31:0] $end
$var wire 1 ) write_en $end
$var wire 32 [ write_data [31:0] $end
$var wire 8 \ addr_index [7:0] $end
$upscope $end
$scope module instruction_memory_instance $end
$var wire 32 ] instruction [31:0] $end
$var wire 32 ^ addr [31:0] $end
$upscope $end
$scope module pc_instance $end
$var wire 1 ! clk $end
$var wire 1 _ pc_en $end
$var wire 32 ` pc_in [31:0] $end
$var wire 1 " rst $end
$var reg 32 a pc_out [31:0] $end
$upscope $end
$scope module regfile_instance $end
$var wire 1 ! clk $end
$var wire 5 b read_addr1 [4:0] $end
$var wire 5 c read_addr2 [4:0] $end
$var wire 1 " rst $end
$var wire 5 d write_addr [4:0] $end
$var wire 32 e write_data [31:0] $end
$var wire 1 & write_en $end
$var wire 32 f read_data2 [31:0] $end
$var wire 32 g read_data1 [31:0] $end
$scope begin $ivl_for_loop0 $end
$var integer 32 h i [31:0] $end
$upscope $end
$upscope $end
$scope module sign_extender_instance $end
$var wire 3 i imm_src [2:0] $end
$var wire 32 j instruction [31:0] $end
$var reg 32 k extended [31:0] $end
$upscope $end
$upscope $end
$upscope $end
$upscope $end
$enddefinitions $end
#0
$dumpvars
b101 k
b10100000000000010010011 j
b0 i
b100000 h
b0 g
b0 f
b101 e
b1 d
b101 c
b0 b
b0 a
b100 `
1_
b0 ^
b10100000000000010010011 ]
b1 \
b0 [
b11010010000010100000011000 Z
b101 Y
b101 X
b0 W
b101 V
b101 U
b0 T
b101 S
b100 R
b101 Q
b101 P
b101 O
b0 N
b10100000000000010010011 M
b11010010000010100000011000 L
b10011 K
b0 J
b100 I
b101 H
b0 G
b0 F
0E
b0 D
b0 C
b0 B
b0 A
b0 @
b0 ?
b10 >
b10011 =
b0 <
b10 ;
b0 :
09
b0 8
b10 7
06
b0 5
b0 4
03
02
b10011 1
b0 0
b0 /
b0 .
1-
0,
b0 +
b0 *
0)
b10011 (
b0 '
1&
b0 %
0$
b0 #
1"
0!
$end
#5
b1 #
b100000 h
1!
#10
0!
#15
1$
1E
b10100000011000 L
b10100000011000 Z
b0 \
b0 S
b0 e
b0 Q
b0 X
b0 Y
b0 V
b0 P
b0 U
b0 O
b0 k
b10 d
b0 c
b100010011 M
b100010011 ]
b100010011 j
b1000 R
b1000 `
b10 #
b100 H
b1000 I
b100 J
b100 ^
b100 a
1!
0"
#20
0!
#25
b0 '
b0 0
b0 C
0$
0E
b11010010000010100000011000 L
b11010010000010100000011000 Z
b1 \
b101 S
b101 e
b10000 O
b10000 k
b1 .
b1 8
b1 <
b1 A
b1 T
b101 Q
b101 X
b101 Y
19
16
b1 7
b1 ;
b1 >
0-
b10 *
b10 4
b10 ?
b10 B
b10 i
0&
b101 G
b101 W
b101 g
b1100011 (
b1100011 1
b1100011 =
b1100011 K
b10000 d
b1 b
b1000100001100011 M
b1000100001100011 ]
b1000100001100011 j
b1100 R
b1100 `
b11 #
b11000 H
b1100 I
b1000 J
b1000 ^
b1000 a
1!
#30
0!
#35
b101 V
0$
0E
b11010010000010100000011000 L
b11010010000010100000011000 Z
b1 \
b101 S
b101 e
b101 P
b101 U
b0 .
b0 8
b0 <
b0 A
b0 T
b101 Q
b101 X
b101 Y
06
b10 7
b10 ;
b10 >
b0 *
b0 4
b0 ?
b0 B
b0 i
1&
b101 F
b101 [
b101 f
b0 G
b0 W
b0 g
b1 O
b1 k
b110011 (
b110011 1
b110011 =
b110011 K
b10 d
b1 c
b10 b
b100010000000100110011 M
b100010000000100110011 ]
b100010000000100110011 j
b10000 R
b10000 `
b100 #
b1101 H
b10000 I
b1100 J
b1100 ^
b1100 a
1!
#40
0!
#45
b11111 V
0$
0E
b11111111111111111111111111111111 P
b11111111111111111111111111111111 U
b11010010000010100000011000 L
b11010010000010100000011000 Z
b1 \
b100 S
b100 e
09
b0 F
b0 [
b0 f
1-
b0 .
b0 8
b0 <
b0 A
b0 T
b100 Q
b100 X
b100 Y
b11111111111111111111111111111111 O
b11111111111111111111111111111111 k
1,
b10011 (
b10011 1
b10011 =
b10011 K
b1 d
b11111 c
b1 b
b101 G
b101 W
b101 g
b11111111111100001000000010010011 M
b11111111111100001000000010010011 ]
b11111111111100001000000010010011 j
b10100 R
b10100 `
b101 #
b1111 H
b10100 I
b10000 J
b10000 ^
b10000 a
1!
#50
0!
#55
b1 '
b1 0
b1 C
1$
1E
b0 V
b0 P
b0 U
19
12
b10 %
b10 /
b10 @
b10 D
b0 7
b0 ;
b0 >
0-
b100 *
b100 4
b100 ?
b100 B
b100 i
b0 .
b0 8
b0 <
b0 A
b0 T
b11111111111111111111111111110100 O
b11111111111111111111111111110100 k
b111 +
b111 5
b111 :
b111 N
b1101111 (
b1101111 1
b1101111 =
b1101111 K
b0 d
b10101 c
b11111 b
b10100000011000 L
b10100000011000 Z
b0 \
b11000 S
b11000 e
b11111111010111111111000001101111 M
b11111111010111111111000001101111 ]
b11111111010111111111000001101111 j
b1000 R
b1000 `
b0 Q
b0 X
b0 Y
b0 G
b0 W
b0 g
b110 #
b1000 H
b11000 I
b10100 J
b10100 ^
b10100 a
1!
#60
0!
#65
b0 '
b0 0
b0 C
0$
0E
b11010010000010100000011000 L
b11010010000010100000011000 Z
b1 \
b100 Q
b100 X
b100 Y
b1 .
b1 8
b1 <
b1 A
b1 T
02
16
b0 %
b0 /
b0 @
b0 D
b1 7
b1 ;
b1 >
b10 *
b10 4
b10 ?
b10 B
b10 i
0&
b100 G
b100 W
b100 g
b10000 O
b10000 k
0,
b0 +
b0 5
b0 :
b0 N
b1100011 (
b1100011 1
b1100011 =
b1100011 K
b10000 d
b0 c
b1 b
b1000100001100011 M
b1000100001100011 ]
b1000100001100011 j
b1100 R
b1100 `
b100 S
b100 e
b111 #
b11000 H
b1100 I
b1000 J
b1000 ^
b1000 a
1!
#70
0!
#75
b11001011111010001100011000 L
b11001011111010001100011000 Z
b10 \
b100 V
b1001 S
b1001 e
b100 P
b100 U
b0 .
b0 8
b0 <
b0 A
b0 T
b1001 Q
b1001 X
b1001 Y
06
b10 7
b10 ;
b10 >
b0 *
b0 4
b0 ?
b0 B
b0 i
1&
b100 F
b100 [
b100 f
b101 G
b101 W
b101 g
b1 O
b1 k
b110011 (
b110011 1
b110011 =
b110011 K
b10 d
b1 c
b10 b
b100010000000100110011 M
b100010000000100110011 ]
b100010000000100110011 j
b10000 R
b10000 `
b1000 #
b1101 H
b10000 I
b1100 J
b1100 ^
b1100 a
1!
#80
0!
#85
b11111 V
0$
0E
b11111111111111111111111111111111 P
b11111111111111111111111111111111 U
b10100000011000 L
b10100000011000 Z
b0 \
b11 S
b11 e
09
b0 F
b0 [
b0 f
1-
b0 .
b0 8
b0 <
b0 A
b0 T
b11 Q
b11 X
b11 Y
b11111111111111111111111111111111 O
b11111111111111111111111111111111 k
1,
b10011 (
b10011 1
b10011 =
b10011 K
b1 d
b11111 c
b1 b
b100 G
b100 W
b100 g
b11111111111100001000000010010011 M
b11111111111100001000000010010011 ]
b11111111111100001000000010010011 j
b10100 R
b10100 `
b1001 #
b1111 H
b10100 I
b10000 J
b10000 ^
b10000 a
1!
#90
0!
#95
b1 '
b1 0
b1 C
1$
1E
b0 V
b10100000011000 L
b10100000011000 Z
b0 \
b0 P
b0 U
19
12
b10 %
b10 /
b10 @
b10 D
b0 7
b0 ;
b0 >
0-
b100 *
b100 4
b100 ?
b100 B
b100 i
b11111111111111111111111111110100 O
b11111111111111111111111111110100 k
b111 +
b111 5
b111 :
b111 N
b1101111 (
b1101111 1
b1101111 =
b1101111 K
b0 d
b10101 c
b11111 b
b11000 S
b11000 e
b11111111010111111111000001101111 M
b11111111010111111111000001101111 ]
b11111111010111111111000001101111 j
b1000 R
b1000 `
b0 Q
b0 X
b0 Y
b0 G
b0 W
b0 g
b1010 #
b1000 H
b11000 I
b10100 J
b10100 ^
b10100 a
1!
#100
0!
#105
b0 '
b0 0
b0 C
0$
0E
b11 Q
b11 X
b11 Y
b1 .
b1 8
b1 <
b1 A
b1 T
02
16
b0 %
b0 /
b0 @
b0 D
b1 7
b1 ;
b1 >
b10 *
b10 4
b10 ?
b10 B
b10 i
0&
b11 G
b11 W
b11 g
b10000 O
b10000 k
0,
b0 +
b0 5
b0 :
b0 N
b1100011 (
b1100011 1
b1100011 =
b1100011 K
b10000 d
b0 c
b1 b
b1000100001100011 M
b1000100001100011 ]
b1000100001100011 j
b1100 R
b1100 `
b11 S
b11 e
b1011 #
b11000 H
b1100 I
b1000 J
b1000 ^
b1000 a
1!
#110
0!
#115
b11 V
b11111111111111111111111111111111 L
b11111111111111111111111111111111 Z
b11 \
b1100 S
b1100 e
b11 P
b11 U
b0 .
b0 8
b0 <
b0 A
b0 T
b1100 Q
b1100 X
b1100 Y
06
b10 7
b10 ;
b10 >
b0 *
b0 4
b0 ?
b0 B
b0 i
1&
b11 F
b11 [
b11 f
b1001 G
b1001 W
b1001 g
b1 O
b1 k
b110011 (
b110011 1
b110011 =
b110011 K
b10 d
b1 c
b10 b
b100010000000100110011 M
b100010000000100110011 ]
b100010000000100110011 j
b10000 R
b10000 `
b1100 #
b1101 H
b10000 I
b1100 J
b1100 ^
b1100 a
1!
#120
0!
#125
b11111 V
0$
0E
b10100000011000 L
b10100000011000 Z
b0 \
b11111111111111111111111111111111 P
b11111111111111111111111111111111 U
b10 S
b10 e
09
b0 F
b0 [
b0 f
1-
b0 .
b0 8
b0 <
b0 A
b0 T
b10 Q
b10 X
b10 Y
b11111111111111111111111111111111 O
b11111111111111111111111111111111 k
1,
b10011 (
b10011 1
b10011 =
b10011 K
b1 d
b11111 c
b1 b
b11 G
b11 W
b11 g
b11111111111100001000000010010011 M
b11111111111100001000000010010011 ]
b11111111111100001000000010010011 j
b10100 R
b10100 `
b1101 #
b1111 H
b10100 I
b10000 J
b10000 ^
b10000 a
1!
#130
0!
#135
b1 '
b1 0
b1 C
1$
1E
b0 V
b10100000011000 L
b10100000011000 Z
b0 \
b0 P
b0 U
19
12
b10 %
b10 /
b10 @
b10 D
b0 7
b0 ;
b0 >
0-
b100 *
b100 4
b100 ?
b100 B
b100 i
b11111111111111111111111111110100 O
b11111111111111111111111111110100 k
b111 +
b111 5
b111 :
b111 N
b1101111 (
b1101111 1
b1101111 =
b1101111 K
b0 d
b10101 c
b11111 b
b11000 S
b11000 e
b11111111010111111111000001101111 M
b11111111010111111111000001101111 ]
b11111111010111111111000001101111 j
b1000 R
b1000 `
b0 Q
b0 X
b0 Y
b0 G
b0 W
b0 g
b1110 #
b1000 H
b11000 I
b10100 J
b10100 ^
b10100 a
1!
#140
0!
#145
b0 '
b0 0
b0 C
0$
0E
b10 Q
b10 X
b10 Y
b1 .
b1 8
b1 <
b1 A
b1 T
02
16
b0 %
b0 /
b0 @
b0 D
b1 7
b1 ;
b1 >
b10 *
b10 4
b10 ?
b10 B
b10 i
0&
b10 G
b10 W
b10 g
b10000 O
b10000 k
0,
b0 +
b0 5
b0 :
b0 N
b1100011 (
b1100011 1
b1100011 =
b1100011 K
b10000 d
b0 c
b1 b
b1000100001100011 M
b1000100001100011 ]
b1000100001100011 j
b1100 R
b1100 `
b10 S
b10 e
b1111 #
b11000 H
b1100 I
b1000 J
b1000 ^
b1000 a
1!
#150
0!
#155
b10 V
b11111111111111111111111111111111 L
b11111111111111111111111111111111 Z
b11 \
b1110 S
b1110 e
b10 P
b10 U
b0 .
b0 8
b0 <
b0 A
b0 T
b1110 Q
b1110 X
b1110 Y
06
b10 7
b10 ;
b10 >
b0 *
b0 4
b0 ?
b0 B
b0 i
1&
b10 F
b10 [
b10 f
b1100 G
b1100 W
b1100 g
b1 O
b1 k
b110011 (
b110011 1
b110011 =
b110011 K
b10 d
b1 c
b10 b
b100010000000100110011 M
b100010000000100110011 ]
b100010000000100110011 j
b10000 R
b10000 `
b10000 #
b1101 H
b10000 I
b1100 J
b1100 ^
b1100 a
1!
#160
0!
#165
b11111 V
0$
0E
b11111111111111111111111111111111 P
b11111111111111111111111111111111 U
b10100000011000 L
b10100000011000 Z
b0 \
b1 S
b1 e
09
b0 F
b0 [
b0 f
1-
b0 .
b0 8
b0 <
b0 A
b0 T
b1 Q
b1 X
b1 Y
b11111111111111111111111111111111 O
b11111111111111111111111111111111 k
1,
b10011 (
b10011 1
b10011 =
b10011 K
b1 d
b11111 c
b1 b
b10 G
b10 W
b10 g
b11111111111100001000000010010011 M
b11111111111100001000000010010011 ]
b11111111111100001000000010010011 j
b10100 R
b10100 `
b10001 #
b1111 H
b10100 I
b10000 J
b10000 ^
b10000 a
1!
#170
0!
#175
b1 '
b1 0
b1 C
b0 V
b10100000011000 L
b10100000011000 Z
b0 \
b0 P
b0 U
19
12
b10 %
b10 /
b10 @
b10 D
b0 7
b0 ;
b0 >
0-
b100 *
b100 4
b100 ?
b100 B
b100 i
b11111111111111111111111111110100 O
b11111111111111111111111111110100 k
b111 +
b111 5
b111 :
b111 N
b1101111 (
b1101111 1
b1101111 =
b1101111 K
b0 d
b10101 c
b11111 b
1$
1E
b11000 S
b11000 e
b11111111010111111111000001101111 M
b11111111010111111111000001101111 ]
b11111111010111111111000001101111 j
b1000 R
b1000 `
b0 Q
b0 X
b0 Y
b0 G
b0 W
b0 g
b10010 #
b1000 H
b11000 I
b10100 J
b10100 ^
b10100 a
1!
#180
0!
#185
b0 '
b0 0
b0 C
0$
0E
b1 Q
b1 X
b1 Y
b1 .
b1 8
b1 <
b1 A
b1 T
02
16
b0 %
b0 /
b0 @
b0 D
b1 7
b1 ;
b1 >
b10 *
b10 4
b10 ?
b10 B
b10 i
0&
b1 G
b1 W
b1 g
b10000 O
b10000 k
0,
b0 +
b0 5
b0 :
b0 N
b1100011 (
b1100011 1
b1100011 =
b1100011 K
b10000 d
b0 c
b1 b
b1000100001100011 M
b1000100001100011 ]
b1000100001100011 j
b1100 R
b1100 `
b1 S
b1 e
b10011 #
b11000 H
b1100 I
b1000 J
b1000 ^
b1000 a
1!
#190
0!
#195
b1 V
b11111111111111111111111111111111 L
b11111111111111111111111111111111 Z
b11 \
b1111 S
b1111 e
b1 P
b1 U
b0 .
b0 8
b0 <
b0 A
b0 T
b1111 Q
b1111 X
b1111 Y
06
b10 7
b10 ;
b10 >
b0 *
b0 4
b0 ?
b0 B
b0 i
1&
b1 F
b1 [
b1 f
b1110 G
b1110 W
b1110 g
b1 O
b1 k
b110011 (
b110011 1
b110011 =
b110011 K
b10 d
b1 c
b10 b
b100010000000100110011 M
b100010000000100110011 ]
b100010000000100110011 j
b10000 R
b10000 `
b10100 #
b1101 H
b10000 I
b1100 J
b1100 ^
b1100 a
1!
#200
0!
