rtl/data_memory.sv
module data_memory(

    input logic clk,
    input logic write_en,
    input logic [31:0] addr,
    input logic [31:0] write_data,
    output logic [31:0] read_data
);

logic [7:0] addr_index;
logic [31:0] memory [255:0];

initial begin
    $readmemh("C:/Users/User/Desktop/project risk v/sim/data.hex",memory);
end

always_ff@(posedge clk) begin
    if(write_en) begin
        memory[addr_index] <= write_data;
    end
end


assign addr_index = addr[9:2];
assign read_data = memory[addr_index];

endmodule

rtl/alu.sv
module alu(
    input [31:0] a,b,
    input [3:0] alu_op,
    output logic [31:0] result,
    output logic zero
);

logic [4:0] shft_amt;

localparam
    ADD = 4'b0000,
    SUB = 4'b0001,
    AND = 4'b0010,
    OR  = 4'b0011,
    XOR = 4'b0100,
    SHL = 4'b0101,
    SHR = 4'b0110,
    SHRA = 4'b0111,
    SLT = 4'b1000,
    SLTU= 4'b1001;

always_comb begin
    
    case(alu_op) 
        
        ADD : result = a + b;

        SUB : result = a - b;
        
        AND : result = a & b;

        OR : result = a | b;

        XOR : result = a ^ b;

        SHL : result = a << shft_amt;

        SHR : result = a >> shft_amt;

        SHRA: result = $signed(a) >>> shft_amt;

        SLT : result = ($signed(a) < $signed(b)) ? 32'b1 : 32'b0;

        SLTU: result = (a < b) ? 32'b1 : 32'b0;

        default: result = 32'b0;

        endcase

        
    end
    

assign zero = (result == 32'b0) ? 1'b1 : 1'b0;
assign shft_amt = b[4:0];


    
endmodule

rtl/sign_extender.sv
module sign_extender(

    input logic [2:0] imm_src,
    input logic [31:0] instruction,
    output logic [31:0] extended
);

localparam i_type = 3'b000;
localparam s_type = 3'b001;
localparam b_type = 3'b010;
localparam u_type = 3'b011;
localparam j_type = 3'b100;

always@(*) begin
    case(imm_src)

    i_type: extended = {{20{instruction[31]}}, instruction[31:20]};

    s_type: extended = {{20{instruction[31]}}, instruction[31:25], instruction[11:7]};

    b_type: extended = {{20{instruction[31]}}, instruction[7], instruction[30:25], instruction[11:8], 1'b0};

    u_type: extended = {{instruction[31:12]}, 12'b0};

    j_type: extended = {{12{instruction[31]}}, instruction[31], instruction[19:12], instruction[20], instruction[30:21], 1'b0};

    default: extended = 32'b0;

    endcase

    end

endmodule

rtl/rtl/register_file.sv
module regfile(
    input logic clk,rst,write_en,
    input logic [4:0] read_addr1, read_addr2, write_addr,
    input logic [31:0] write_data,
    output logic [31:0] read_data1, read_data2
);

logic [31:0] registers [31:0];

always_ff@(posedge clk or posedge rst) begin
    if(rst) begin
        for(int i=0;i<32;i++) begin
            registers[i]<= 32'b0;
        end
    end else if(write_en & (write_addr != 5'b0)) 
        registers[write_addr] <= write_data;
    
    end

assign read_data1 = (read_addr1 == 5'b0) ? 32'b0 : registers[read_addr1];
assign read_data2 = (read_addr2 == 5'b0) ? 32'b0 : registers[read_addr2];

endmodule

rtl/instruction_memory.sv
module instruction_memory(

    input logic [31:0] addr,
    output logic [31:0] instruction
);

logic [31:0] instruction_mem [0:255];

initial begin
    $readmemh("instruction_data_sum_arr.hex", instruction_mem);
end

assign instruction = instruction_mem[addr[9:2]]; // word aligned address + reduced to 8 bits for 256 instructions

endmodule

rtl/rtl/pc.sv
module pc(
    input logic clk,
    input logic rst,
    input logic pc_en,
    input logic [31:0] pc_in,
    output logic [31:0] pc_out
);

always_ff@(posedge clk or posedge rst) begin
    if(rst) begin
        pc_out <= 32'b0;
    end else if(pc_en) begin
        pc_out <= pc_in;
    end

end

endmodule

rtl/rtl/datapath.sv
module datapath(

    input logic clk,
    input logic rst,
    input logic alu_src,
    input logic [1:0] pc_src,
    input logic reg_write,
    input logic [3:0] alu_ctrl,
    input logic [2:0] imm_src,
    input logic mem_write,
    input logic [2:0] result_src,
    output logic [6:0] op_code,
    output logic bit30func7,
    output logic [2:0] func3,
    output logic zero_flag
);

logic [31:0] pc_current;
logic [31:0] pc_next;
logic [31:0] instruction;
logic [31:0] read_data1;
logic [31:0] read_data2;
logic [31:0] extended;
logic [31:0] b;
logic [31:0] alu_result;
logic zero;
logic [31:0] mem_read_data;
logic [31:0] write_back_data;
logic [31:0] pc_target;
logic [31:0] pc_inc;


//temp control wires
/////////

pc pc_instance(
    .clk(clk),
    .rst(rst),
    .pc_en(1'b1), //temp
    .pc_in(pc_next),
    .pc_out(pc_current)
);

instruction_memory instruction_memory_instance(
    .addr(pc_current),
    .instruction(instruction)
);

regfile regfile_instance(
    .clk(clk),
    .rst(rst),
    .write_en(reg_write),
    .read_addr1(instruction[19:15]),
    .read_addr2(instruction[24:20]),
    .write_addr(instruction[11:7]),
    .write_data(write_back_data), 
    .read_data1(read_data1),
    .read_data2(read_data2)
);

sign_extender sign_extender_instance(
    .imm_src(imm_src), // 
    .instruction(instruction),
    .extended(extended)
);

alu alu_instance(
    .a(read_data1),
    .b(b),
    .alu_op(alu_ctrl),
    .zero(zero),
    .result(alu_result)
);

data_memory data_memory_instance(
    .clk(clk),
    .write_en(mem_write),//
    .addr(alu_result),
    .write_data(read_data2),
    .read_data(mem_read_data)
);







always_comb begin
    case(result_src)
        3'b000: write_back_data = alu_result;
        3'b001: write_back_data = mem_read_data;
        3'b010: write_back_data = pc_inc;
        3'b011: write_back_data = extended;
        3'b100: write_back_data = pc_target;
        default: write_back_data = 32'b0;
    endcase
end

always_comb begin
    case(pc_src)
    2'b00: pc_next = pc_inc;
    2'b01: pc_next = pc_target;
    2'b10: pc_next = alu_result;
    default: pc_next = pc_inc;
    endcase
end

assign pc_inc = pc_current + 32'd4;
assign pc_target = pc_current + extended;
assign b = (alu_src)? extended:read_data2;
assign op_code = instruction[6:0];
assign func3 = instruction[14:12];
assign bit30func7 = instruction[30];
assign zero_flag = zero;


endmodule

rtl/control_unit_alu_decoder.sv
module control_unit_alu_decoder(
    input logic [1:0] alu_op,
    input logic [2:0] func3,
    input logic bit30func7,
    input logic op5,
    output logic [3:0] alu_ctrl
);

localparam add = 2'b00;
localparam sub = 2'b01;
localparam other = 2'b10;

always_comb begin 
    case(alu_op)
        add: alu_ctrl = 4'b0000;
        sub: alu_ctrl = 4'b0001;
        other: begin
            case(func3)
                3'b000: begin
                    if(op5 & bit30func7)
                        alu_ctrl = 4'b0001;
                    else
                        alu_ctrl = 4'b0000;
                end
                3'b010: alu_ctrl = 4'b1000;
               
                3'b110: alu_ctrl = 4'b0011;

                3'b111: alu_ctrl = 4'b0010;  

                default: alu_ctrl = 4'b0000;
            endcase
        end
        default: alu_ctrl = 4'b0000;

    endcase
    
end


endmodule

rtl/control_unit_main_decoder.sv
module control_unit_main_decoder(
input logic [6:0] op_code,
output logic branch,
output logic jump,
output logic jalr,
output logic [2:0] result_src,
output logic mem_write,
output logic [1:0] alu_op, //00 add 01 sub 10 let func3and7 decide
output logic alu_src,
output logic [2:0] imm_ctrl,
output logic reg_write
);


localparam  lw = 7'b0000011;
localparam  sw = 7'b0100011;
localparam r_type = 7'b0110011;
localparam i_type = 7'b0010011;
localparam beq = 7'b1100011;
localparam jal = 7'b1101111;
localparam jalr_op = 7'b1100111;
localparam lui = 7'b0110111;
localparam auipc = 7'b0010111;
localparam nop = 13'b0000000000000;


always_comb begin
    case(op_code)

        lw:      {jalr, jump, branch, result_src, mem_write, alu_op, alu_src, imm_ctrl, reg_write} = 14'b0_0_0_001_0_00_1_000_1;
        sw:      {jalr, jump, branch, result_src, mem_write, alu_op, alu_src, imm_ctrl, reg_write} = 14'b0_0_0_000_1_00_1_001_0;
        r_type:  {jalr, jump, branch, result_src, mem_write, alu_op, alu_src, imm_ctrl, reg_write} = 14'b0_0_0_000_0_10_0_000_1;
        i_type:  {jalr, jump, branch, result_src, mem_write, alu_op, alu_src, imm_ctrl, reg_write} = 14'b0_0_0_000_0_10_1_000_1;
        beq:     {jalr, jump, branch, result_src, mem_write, alu_op, alu_src, imm_ctrl, reg_write} = 14'b0_0_1_000_0_01_0_010_0;
        jal:     {jalr, jump, branch, result_src, mem_write, alu_op, alu_src, imm_ctrl, reg_write} = 14'b0_1_0_010_0_00_0_100_1;
        jalr_op: {jalr, jump, branch, result_src, mem_write, alu_op, alu_src, imm_ctrl, reg_write} = 14'b1_0_0_010_0_00_1_000_1;
        lui:     {jalr, jump, branch, result_src, mem_write, alu_op, alu_src, imm_ctrl, reg_write} = 14'b0_0_0_011_0_00_1_011_1; 
        auipc:   {jalr, jump, branch, result_src, mem_write, alu_op, alu_src, imm_ctrl, reg_write} = 14'b0_0_0_100_0_00_1_011_1; 
        default: {jalr, jump, branch, result_src, mem_write, alu_op, alu_src, imm_ctrl, reg_write} = nop;
    endcase
end


endmodule

rtl/control_unit.sv
module control_unit(

    input logic [6:0] op_code,
    input logic [2:0] func3,
    input logic bit30func7,
    input logic zero,
    output logic [1:0] pc_src,
    output logic [2:0] result_src,
    output logic mem_write,
    output logic [3:0] alu_ctrl,
    output logic alu_src,
    output logic [2:0] imm_ctrl,
    output logic reg_write
);

logic [1:0] alu_op;
logic branch;
logic jump;
logic jalr;

control_unit_main_decoder control_unit_main_decoder_instance(
    .op_code(op_code),
    .jump(jump),
    .jalr(jalr),
    .branch(branch),
    .result_src(result_src),
    .mem_write(mem_write),
    .alu_op(alu_op),
    .alu_src(alu_src),
    .imm_ctrl(imm_ctrl),
    .reg_write(reg_write)
);

control_unit_alu_decoder control_unit_alu_decoder_instance(
    .alu_op(alu_op),
    .func3(func3),
    .bit30func7(bit30func7),
    .op5(op_code[5]),
    .alu_ctrl(alu_ctrl)
);

assign pc_src = jalr ? 2'b10 : (jump | (branch & zero)) ? 2'b01 : 2'b00;

endmodule

rtl/rtl/risc_v_top.sv
module risc_v_top(
    input logic clk,
    input logic rst
);

logic alu_src;
logic [1:0] pc_src;
logic reg_write;
logic [3:0] alu_ctrl;
logic [2:0] imm_src;
logic mem_write;
logic [2:0] result_src;
logic [6:0] op_code;
logic bit30func7;
logic [2:0] func3;
logic zero_flag;

control_unit control_unit_instance(
    .op_code(op_code),
    .func3(func3),
    .bit30func7(bit30func7),
    .zero(zero_flag),
    .pc_src(pc_src),
    .result_src(result_src),
    .mem_write(mem_write),
    .alu_ctrl(alu_ctrl),
    .alu_src(alu_src),
    .imm_ctrl(imm_src),
    .reg_write(reg_write)
);

datapath datapath_instance(
    .clk(clk),
    .rst(rst),
    .alu_src(alu_src),
    .pc_src(pc_src),
    .reg_write(reg_write),
    .alu_ctrl(alu_ctrl),
    .imm_src(imm_src),
    .mem_write(mem_write),
    .result_src(result_src),
    .op_code(op_code),
    .bit30func7(bit30func7),
    .func3(func3),
    .zero_flag(zero_flag)
);

endmodule

tb/risc_v_top_tb.sv
module risc_v_top_tb;

    logic clk;
    logic rst;

    risc_v_top dut(
        .clk(clk),
        .rst(rst)
    );

    always #5 clk = ~clk; //generate clock

    initial begin
        $dumpfile("sim/dump.vcd"); //create a dump file
        $dumpvars(0, risc_v_top_tb);

        clk = 1'b0; //initialize system
        rst = 1'b1;
        #15

        rst = 1'b0;// let the system run
        #200

        $finish;
    end

endmodule

dump.vcd
$date
	Thu Sep 17 13:33:25 2026
$end
$version
	Icarus Verilog
$end
$timescale
	1s
$end
$scope module risc_v_top_tb $end
$var reg 1 ! clk $end
$var reg 1 " rst $end
$scope module dut $end
$var wire 1 ! clk $end
$var wire 1 " rst $end
$var wire 1 # zero_flag $end
$var wire 3 $ result_src [2:0] $end
$var wire 1 % reg_write $end
$var wire 2 & pc_src [1:0] $end
$var wire 7 ' op_code [6:0] $end
$var wire 1 ( mem_write $end
$var wire 3 ) imm_src [2:0] $end
$var wire 3 * func3 [2:0] $end
$var wire 1 + bit30func7 $end
$var wire 1 , alu_src $end
$var wire 4 - alu_ctrl [3:0] $end
$scope module control_unit_instance $end
$var wire 1 # zero $end
$var wire 3 . result_src [2:0] $end
$var wire 1 % reg_write $end
$var wire 2 / pc_src [1:0] $end
$var wire 7 0 op_code [6:0] $end
$var wire 1 ( mem_write $end
$var wire 1 1 jump $end
$var wire 1 2 jalr $end
$var wire 3 3 imm_ctrl [2:0] $end
$var wire 3 4 func3 [2:0] $end
$var wire 1 5 branch $end
$var wire 1 + bit30func7 $end
$var wire 1 , alu_src $end
$var wire 2 6 alu_op [1:0] $end
$var wire 4 7 alu_ctrl [3:0] $end
$scope module control_unit_alu_decoder_instance $end
$var wire 1 8 op5 $end
$var wire 3 9 func3 [2:0] $end
$var wire 1 + bit30func7 $end
$var wire 2 : alu_op [1:0] $end
$var reg 4 ; alu_ctrl [3:0] $end
$upscope $end
$scope module control_unit_main_decoder_instance $end
$var wire 7 < op_code [6:0] $end
$var reg 2 = alu_op [1:0] $end
$var reg 1 , alu_src $end
$var reg 1 5 branch $end
$var reg 3 > imm_ctrl [2:0] $end
$var reg 1 2 jalr $end
$var reg 1 1 jump $end
$var reg 1 ( mem_write $end
$var reg 1 % reg_write $end
$var reg 3 ? result_src [2:0] $end
$upscope $end
$upscope $end
$scope module datapath_instance $end
$var wire 4 @ alu_ctrl [3:0] $end
$var wire 1 , alu_src $end
$var wire 1 ! clk $end
$var wire 3 A imm_src [2:0] $end
$var wire 1 ( mem_write $end
$var wire 2 B pc_src [1:0] $end
$var wire 1 % reg_write $end
$var wire 3 C result_src [2:0] $end
$var wire 1 " rst $end
$var wire 1 # zero_flag $end
$var wire 1 D zero $end
$var wire 32 E read_data2 [31:0] $end
$var wire 32 F read_data1 [31:0] $end
$var wire 32 G pc_target [31:0] $end
$var wire 32 H pc_inc [31:0] $end
$var wire 32 I pc_current [31:0] $end
$var wire 7 J op_code [6:0] $end
$var wire 32 K mem_read_data [31:0] $end
$var wire 32 L instruction [31:0] $end
$var wire 3 M func3 [2:0] $end
$var wire 32 N extended [31:0] $end
$var wire 1 + bit30func7 $end
$var wire 32 O b [31:0] $end
$var wire 32 P alu_result [31:0] $end
$var reg 32 Q pc_next [31:0] $end
$var reg 32 R write_back_data [31:0] $end
$scope module alu_instance $end
$var wire 4 S alu_op [3:0] $end
$var wire 32 T b [31:0] $end
$var wire 1 D zero $end
$var wire 5 U shft_amt [4:0] $end
$var wire 32 V a [31:0] $end
$var reg 32 W result [31:0] $end
$upscope $end
$scope module data_memory_instance $end
$var wire 32 X addr [31:0] $end
$var wire 1 ! clk $end
$var wire 32 Y read_data [31:0] $end
$var wire 1 ( write_en $end
$var wire 32 Z write_data [31:0] $end
$var wire 8 [ addr_index [7:0] $end
$upscope $end
$scope module instruction_memory_instance $end
$var wire 32 \ instruction [31:0] $end
$var wire 32 ] addr [31:0] $end
$upscope $end
$scope module pc_instance $end
$var wire 1 ! clk $end
$var wire 1 ^ pc_en $end
$var wire 32 _ pc_in [31:0] $end
$var wire 1 " rst $end
$var reg 32 ` pc_out [31:0] $end
$upscope $end
$scope module regfile_instance $end
$var wire 1 ! clk $end
$var wire 5 a read_addr1 [4:0] $end
$var wire 5 b read_addr2 [4:0] $end
$var wire 1 " rst $end
$var wire 5 c write_addr [4:0] $end
$var wire 32 d write_data [31:0] $end
$var wire 1 % write_en $end
$var wire 32 e read_data2 [31:0] $end
$var wire 32 f read_data1 [31:0] $end
$scope begin $ivl_for_loop0 $end
$var integer 32 g i [31:0] $end
$upscope $end
$upscope $end
$scope module sign_extender_instance $end
$var wire 3 h imm_src [2:0] $end
$var wire 32 i instruction [31:0] $end
$var reg 32 j extended [31:0] $end
$upscope $end
$upscope $end
$upscope $end
$upscope $end
$enddefinitions $end
#0
$dumpvars
b1000000000000 j
b1000010110111 i
b11 h
b100000 g
b0 f
b0 e
b1000000000000 d
b1 c
b0 b
b0 a
b0 `
b100 _
1^
b0 ]
b1000010110111 \
b0 [
b0 Z
b10100000011000 Y
b1000000000000 X
b1000000000000 W
b0 V
b0 U
b1000000000000 T
b0 S
b1000000000000 R
b100 Q
b1000000000000 P
b1000000000000 O
b1000000000000 N
b1 M
b1000010110111 L
b10100000011000 K
b110111 J
b0 I
b100 H
b1000000000000 G
b0 F
b0 E
0D
b11 C
b0 B
b11 A
b0 @
b11 ?
b11 >
b0 =
b110111 <
b0 ;
b0 :
b1 9
18
b0 7
b0 6
05
b1 4
b11 3
02
01
b110111 0
b0 /
b11 .
b0 -
1,
0+
b1 *
b11 )
0(
b110111 '
b0 &
1%
b11 $
0#
1"
0!
$end
#5
b100000 g
1!
#10
0!
#15
bx K
bx Y
b11111111 [
b11111 U
b111111111111 R
b111111111111 d
b11111111111111111111111111111111 O
b11111111111111111111111111111111 T
b111111111111 P
b111111111111 W
b111111111111 X
08
b0 $
b0 .
b0 ?
b0 C
b10 6
b10 :
b10 =
b0 )
b0 3
b0 >
b0 A
b0 h
b1000000000000 F
b1000000000000 V
b1000000000000 f
b11111111111111111111111111111111 N
b11111111111111111111111111111111 j
1+
b0 *
b0 4
b0 9
b0 M
b10011 '
b10011 0
b10011 <
b10011 J
b10 c
b11111 b
b1 a
b11111111111100001000000100010011 L
b11111111111100001000000100010011 \
b11111111111100001000000100010011 i
b1000 Q
b1000 _
b11 G
b1000 H
b100 I
b100 ]
b100 `
1!
0"
#20
0!
#25
b0 U
b1111111111111 R
b1111111111111 d
b1000000000000 O
b1000000000000 T
b1111111111111 P
b1111111111111 W
b1111111111111 X
18
0,
b1000000000000 E
b1000000000000 Z
b1000000000000 e
b111111111111 F
b111111111111 V
b111111111111 f
b1 N
b1 j
0+
b110011 '
b110011 0
b110011 <
b110011 J
b11 c
b1 b
b10 a
b100010000000110110011 L
b100010000000110110011 \
b100010000000110110011 i
b1100 Q
b1100 _
b1001 G
b1100 H
b1000 I
b1000 ]
b1000 `
1!
#30
0!
#35
b100 U
b11010010000010100000011000 K
b11010010000010100000011000 Y
b1 [
b100 R
b100 d
b100 O
b100 T
b100 P
b100 W
b100 X
1(
b0 6
b0 :
b0 =
1,
b1 )
b1 3
b1 >
b1 A
b1 h
0%
b1111111111111 E
b1111111111111 Z
b1111111111111 e
b0 F
b0 V
b0 f
b100 N
b100 j
b10 *
b10 4
b10 9
b10 M
b100011 '
b100011 0
b100011 <
b100011 J
b100 c
b11 b
b0 a
b1100000010001000100011 L
b1100000010001000100011 \
b1100000010001000100011 i
b10000 Q
b10000 _
b10000 G
b10000 H
b1100 I
b1100 ]
b1100 `
1!
#40
0!
#45
b1111111111111 R
b1111111111111 d
08
b1 $
b1 .
b1 ?
b1 C
0(
b0 )
b0 3
b0 >
b0 A
b0 h
1%
b0 E
b0 Z
b0 e
b11 '
b11 0
b11 <
b11 J
b100 b
b10000000010001000000011 L
b10000000010001000000011 \
b10000000010001000000011 i
b10100 Q
b10100 _
b1111111111111 K
b1111111111111 Y
b10100 G
b10100 H
b10000 I
b10000 ]
b10000 `
1!
#50
0!
#55
b1 &
b1 /
b1 B
1#
1D
b11111 U
b10100000011000 K
b10100000011000 Y
b0 [
b0 R
b0 d
b1111111111111 O
b1111111111111 T
b1000 N
b1000 j
b0 P
b0 W
b0 X
b1 -
b1 7
b1 ;
b1 @
b1 S
18
15
b0 $
b0 .
b0 ?
b0 C
b1 6
b1 :
b1 =
0,
b10 )
b10 3
b10 >
b10 A
b10 h
0%
b1111111111111 F
b1111111111111 V
b1111111111111 f
b0 *
b0 4
b0 9
b0 M
b1100011 '
b1100011 0
b1100011 <
b1100011 J
b1000 c
b11 a
b10000011000010001100011 L
b10000011000010001100011 \
b10000011000010001100011 i
b11100 Q
b11100 _
b1111111111111 E
b1111111111111 Z
b1111111111111 e
b11100 G
b11000 H
b10100 I
b10100 ]
b10100 `
1!
#60
0!
#65
b0 U
1#
1D
b0 O
b0 T
b0 -
b0 7
b0 ;
b0 @
b0 S
b0 P
b0 W
b0 X
b100000 R
b100000 d
11
05
b10 $
b10 .
b10 ?
b10 C
b0 6
b0 :
b0 =
b100 )
b100 3
b100 >
b100 A
b100 h
1%
b0 E
b0 Z
b0 e
b0 F
b0 V
b0 f
b0 N
b0 j
b1101111 '
b1101111 0
b1101111 <
b1101111 J
b0 c
b0 b
b0 a
b1101111 L
b1101111 \
b1101111 i
b11100 Q
b11100 _
b11100 G
b100000 H
b11100 I
b11100 ]
b11100 `
1!
